djangoldp_profile/__init__.py
djangoldp_profile/admin.py
djangoldp_profile/apps.py
djangoldp_profile/factories.py
djangoldp_profile/models.py
djangoldp_profile/settings.py
djangoldp_profile/management/__init__.py
djangoldp_profile/management/commands/__init__.py
djangoldp_profile/management/commands/mock_profile.py
djangoldp_profile/migrations/0001_initial.py
djangoldp_profile/migrations/0002_auto_20190917_1141.py
djangoldp_profile/migrations/0003_auto_20200416_1157.py
djangoldp_profile/migrations/0004_auto_20200506_0838.py
djangoldp_profile/migrations/0005_auto_20200522_1516.py
djangoldp_profile/migrations/0006_auto_20200610_1323.py
djangoldp_profile/migrations/0007_auto_20200617_1817.py
djangoldp_profile/migrations/0008_alter_profile_available.py
djangoldp_profile/migrations/0009_alter_profile_urlid.py
djangoldp_profile/migrations/0010_add_timestamps_to_models.py
djangoldp_profile/migrations/__init__.py
djangoldp_profile-5.0.0.dist-info/METADATA
djangoldp_profile-5.0.0.dist-info/WHEEL
djangoldp_profile-5.0.0.dist-info/top_level.txt
djangoldp_profile-5.0.0.dist-info/RECORD
